{
    "flair.app": {
        "app": "myapp.main.App",

        "boot": {
            "env": {
                "isVue": true
            },
            "links": [
                { "rel": "stylesheet", "href": "https://maxcdn.bootstrapcdn.com/bootstrap/4.0.0/css/bootstrap{.min}.css" },
                { "rel": "stylesheet", "href": "./assets/css/styles{.min}.css" }
            ],            
            "preambles": [
                "./app"
            ]
        },

        "api": {
            "connections": {
                "api-server": {
                    "url": "http://localhost:8080/api/v1/",
                    "options": {
                        "get": {
                            "method": "GET",
                            "mode": "cors",
                            "headers": {
                                "Content-Type": "application/json"
                            }                            
                        },
                        "post": {
                            "method": "POST",
                            "mode": "cors",
                            "cache": "no-cache",
                            "credentials": "same-origin",
                            "headers": {
                                "Content-Type": "application/json"
                            },
                            "redirect": "follow",
                            "referrer": "no-referrer"
                        }
                    }
                }
            }
        }        
    },

    "flair.client": {
        "view": {
            "layout": "./assets/layouts/default{.min}.html",
            "routes": {
                "home": "myapp.views.home",
                "notfound": "myapp.views.notfound"
            }
        }, 

        "i18n": {
            "lang": {
                "default": "en",
                "locales": [
                    { "code": "en", "name": "English", "native": "English" },
                    { "code": "hi", "name": "Hindi", "native": "हिंदी" }
                ]
            }
        },

        "routing": {
            "mounts": {
                "main": "/"
            },
            "all": {
                "before": {
                    "settings": [
                        { "name": "hashbang", "value": false },
                        { "name": "lang", "value": false },
                        { "name": "sensitive", "value": false }
                    ]
                }
            }
        }
    }
}